simplepysite/__init__.py
simplepysite/__main__.py
simplepysite/site.py
simplepysite-0.1.3.dist-info/METADATA
simplepysite-0.1.3.dist-info/WHEEL
simplepysite-0.1.3.dist-info/license.txt
simplepysite-0.1.3.dist-info/top_level.txt
simplepysite-0.1.3.dist-info/RECORD
