Metadata-Version: 2.1
Name: simplepysite
Version: 0.1.3
Summary: Simple static site generator
Home-page: https://github.com/paloblanco/simplepysite
Author: Rocco Panella
Author-email: panella.rocco@gmail.com
License: MIT
License-File: license.txt
Requires-Dist: markdown
